codenamize/__init__.py
codenamize/codenamize.py
codenamize/__pycache__/__init__.cpython-35.pyc
codenamize/__pycache__/codenamize.cpython-35.pyc
codenamize-1.2.3.dist-info/DESCRIPTION.rst
codenamize-1.2.3.dist-info/METADATA
codenamize-1.2.3.dist-info/RECORD
codenamize-1.2.3.dist-info/WHEEL
codenamize-1.2.3.dist-info/entry_points.txt
codenamize-1.2.3.dist-info/metadata.json
codenamize-1.2.3.dist-info/top_level.txt
